[{"category":"gebouw","routeid":"mdfg","tilename":"Fort Meuse","name":"Fort de Gènicourt","description":"Fort de Gènicourt","rating":5,"visitdate":200903},{"category":"spoor","routeid":"l154","tilename":"Ligne 154","name":"Ligne 154","description":"Ligne 154","rating":5,"visitdate":200808},{"category":"tunnel","routeid":"tgi","tilename":"Charlemont","name":"Tunnel de Charlemont","description":"Tunnel de Charlemont","rating":5,"visitdate":200808},{"category":"brug","routeid":"vdf","tilename":"Viaduc des Fades","name":"Viaduc des Fades","description":"Viaduc des Fades","rating":5,"visitdate":200612},{"category":"xerbutri","routeid":"txatx","tilename":"Sur TX","name":"Sur Team Xerbutri","description":"Sur Team Xerbutri","rating":4,"visitdate":199801},{"category":"xerbutri","routeid":"txaue","tilename":"Sur UE","name":"Exploration urbaine","description":"Exploration urbaine","rating":1,"visitdate":199801}]